Metadata-Version: 2.4
Name: whisperlivekit
Version: 0.2.17.post1
Summary: Real-time speech-to-text with speaker diarization using Whisper
Author: Quentin Fuxa
License:                                  Apache License
Project-URL: Homepage, https://github.com/QuentinFuxa/WhisperLiveKit
Classifier: Development Status :: 4 - Beta
Classifier: Intended Audience :: Developers
Classifier: License :: OSI Approved :: MIT License
Classifier: Programming Language :: Python :: 3.9
Classifier: Programming Language :: Python :: 3.10
Classifier: Programming Language :: Python :: 3.11
Classifier: Programming Language :: Python :: 3.12
Classifier: Programming Language :: Python :: 3.13
Classifier: Programming Language :: Python :: 3.14
Classifier: Programming Language :: Python :: 3.15
Classifier: Topic :: Scientific/Engineering :: Artificial Intelligence
Classifier: Topic :: Multimedia :: Sound/Audio :: Speech
Requires-Python: >=3.9
License-File: LICENSE
Requires-Dist: fastapi
Requires-Dist: librosa
Requires-Dist: soundfile
Requires-Dist: uvicorn
Requires-Dist: websockets
Requires-Dist: torchaudio>=2.0.0
Requires-Dist: torch>=2.0.0
Requires-Dist: huggingface-hub>=0.25.0
Requires-Dist: faster-whisper>=1.2.0
Requires-Dist: tqdm
Requires-Dist: tiktoken
Requires-Dist: triton>=2.0.0; platform_machine == "x86_64" and (sys_platform == "linux" or sys_platform == "linux2")
Provides-Extra: translation
Requires-Dist: nllw; extra == "translation"
Provides-Extra: sentence-tokenizer
Requires-Dist: mosestokenizer; extra == "sentence-tokenizer"
Requires-Dist: wtpsplit; extra == "sentence-tokenizer"
Dynamic: license-file
